github_pr_watcher/github_auth.py
github_pr_watcher/github_prs_client.py
github_pr_watcher/main.py
github_pr_watcher/notifications.py
github_pr_watcher/objects.py
github_pr_watcher/resources/icon.png
github_pr_watcher/settings.py
github_pr_watcher/ui/__init__.py
github_pr_watcher/ui/combo_box.py
github_pr_watcher/ui/filters.py
github_pr_watcher/ui/main_window.py
github_pr_watcher/ui/pr_card.py
github_pr_watcher/ui/refresh_worker.py
github_pr_watcher/ui/section_frame.py
github_pr_watcher/ui/settings_dialog.py
github_pr_watcher/ui/stats_dialog.py
github_pr_watcher/ui/themes.py
github_pr_watcher/ui/ui_state.py
github_pr_watcher/utils.py
github_pr_watcher-1.27.0.dist-info/LICENSE
github_pr_watcher-1.27.0.dist-info/METADATA
github_pr_watcher-1.27.0.dist-info/WHEEL
github_pr_watcher-1.27.0.dist-info/entry_points.txt
github_pr_watcher-1.27.0.dist-info/RECORD
