Metadata-Version: 2.1
Name: github-pr-watcher
Version: 1.27.0
Summary: A MacOs UI tool to monitor GitHub Pull Requests
Home-page: https://github.com/gm2211/github-watcher
License: AGPL-3.0-or-later
Author: gm2211
Author-email: gmecocci@outlook.com
Requires-Python: >=3.10,<=3.14
Classifier: License :: OSI Approved :: GNU Affero General Public License v3 or later (AGPLv3+)
Classifier: Programming Language :: Python :: 3
Classifier: Programming Language :: Python :: 3.10
Classifier: Programming Language :: Python :: 3.11
Classifier: Programming Language :: Python :: 3.12
Classifier: Programming Language :: Python :: 3.13
Requires-Dist: PyQt6 (>=6.6.1,<7.0.0)
Requires-Dist: matplotlib (>=3.8.2,<4.0.0)
Requires-Dist: numpy (>=2.1.3,<3.0.0)
Requires-Dist: pyyaml (>=6.0.1,<7.0.0)
Requires-Dist: requests (>=2.31.0,<3.0.0)
Requires-Dist: seaborn (>=0.13.1,<0.14.0)
Requires-Dist: tomli (>=2.0.1,<3.0.0)
Project-URL: Repository, https://github.com/gm2211/github-watcher
